beetsplug/__init__.py
beetsplug/mosaic.py
beets_mosaic-0.9.3.dist-info/LICENSE
beets_mosaic-0.9.3.dist-info/METADATA
beets_mosaic-0.9.3.dist-info/WHEEL
beets_mosaic-0.9.3.dist-info/top_level.txt
beets_mosaic-0.9.3.dist-info/RECORD
