Metadata-Version: 2.1
Name: beets-mosaic
Version: 0.9.3
Summary: Plugin for the music library manager Beets. The mosaic plugin generates a montage of a mosiac from cover art.
Home-page: https://github.com/susannamaria/beets-mosaic
Download-URL: https://github.com/SusannaMaria/beets-mosaic.git
Author: Susanna Maria Hepp
Author-email: susanna@olsoni.de
License: MIT
Keywords: beets mosaic
Classifier: License :: OSI Approved :: MIT License
Classifier: Programming Language :: Python :: 3
Classifier: Programming Language :: Python :: 3.4
Classifier: Programming Language :: Python :: 3.5
Classifier: Programming Language :: Python :: 3.6
License-File: LICENSE
Requires-Dist: beets >=1.4.3
Requires-Dist: Pillow
Requires-Dist: Parse
Requires-Dist: TTFQuery >=2.0.0b1
Requires-Dist: fontTools
Requires-Dist: requests
